event_sourcery/__init__.py
event_sourcery/_event_store/__init__.py
event_sourcery/_event_store/backend.py
event_sourcery/_event_store/event/__init__.py
event_sourcery/_event_store/event/dto.py
event_sourcery/_event_store/event/encryption.py
event_sourcery/_event_store/event/registry.py
event_sourcery/_event_store/event/serde.py
event_sourcery/_event_store/event_store.py
event_sourcery/_event_store/in_memory.py
event_sourcery/_event_store/outbox.py
event_sourcery/_event_store/stream_id.py
event_sourcery/_event_store/subscription/__init__.py
event_sourcery/_event_store/subscription/builder.py
event_sourcery/_event_store/subscription/in_transaction.py
event_sourcery/_event_store/subscription/interfaces.py
event_sourcery/_event_store/tenant_id.py
event_sourcery/_event_store/versioning.py
event_sourcery/backend.py
event_sourcery/encryption.py
event_sourcery/event.py
event_sourcery/event_sourcing/__init__.py
event_sourcery/event_sourcing/aggregate.py
event_sourcery/event_sourcing/repository.py
event_sourcery/exceptions.py
event_sourcery/in_transaction.py
event_sourcery/interfaces.py
event_sourcery/outbox.py
event_sourcery/py.typed
event_sourcery/read_model/__init__.py
event_sourcery/read_model/cursors_dao.py
event_sourcery/read_model/projector.py
event_sourcery/subscription.py
event_sourcery_django/__init__.py
event_sourcery_django/dto.py
event_sourcery_django/event_store.py
event_sourcery_django/migrations/0001_initial.py
event_sourcery_django/migrations/__init__.py
event_sourcery_django/models.py
event_sourcery_django/outbox.py
event_sourcery_django/py.typed
event_sourcery_django/subscription.py
event_sourcery_kurrentdb/__init__.py
event_sourcery_kurrentdb/dto.py
event_sourcery_kurrentdb/event_store.py
event_sourcery_kurrentdb/outbox.py
event_sourcery_kurrentdb/py.typed
event_sourcery_kurrentdb/stream.py
event_sourcery_kurrentdb/subscription.py
event_sourcery_sqlalchemy/__init__.py
event_sourcery_sqlalchemy/cursors_dao.py
event_sourcery_sqlalchemy/dto.py
python_event_sourcery-0.5.0.dist-info/LICENSE
python_event_sourcery-0.5.0.dist-info/METADATA
python_event_sourcery-0.5.0.dist-info/WHEEL
python_event_sourcery-0.5.0.dist-info/RECORD
