Metadata-Version: 2.3
Name: python-event-sourcery
Version: 0.5.0
Summary: A library for event-based systems in Python.
License: MIT
Author: Sebastian Buczyński
Author-email: nnplaya@gmail.com
Requires-Python: >=3.10
Classifier: License :: OSI Approved :: MIT License
Classifier: Programming Language :: Python :: 3
Classifier: Programming Language :: Python :: 3.10
Classifier: Programming Language :: Python :: 3.11
Classifier: Programming Language :: Python :: 3.12
Classifier: Programming Language :: Python :: 3.13
Provides-Extra: django
Provides-Extra: kurrentdb
Provides-Extra: sqlalchemy
Requires-Dist: SQLAlchemy (>=2.0) ; extra == "sqlalchemy"
Requires-Dist: django (>=4,<6) ; extra == "django"
Requires-Dist: kurrentdbclient (>=1.0.6) ; extra == "kurrentdb"
Requires-Dist: more-itertools
Requires-Dist: psycopg2-binary (>2,<3)
Requires-Dist: pydantic (>=2.0,<3)
